timely_beliefs/__init__.py
timely_beliefs/db_base.py
timely_beliefs/utils.py
timely_beliefs/beliefs/__init__.py
timely_beliefs/beliefs/classes.py
timely_beliefs/beliefs/probabilistic_utils.py
timely_beliefs/beliefs/queries.py
timely_beliefs/beliefs/utils.py
timely_beliefs/docs/accuracy.md
timely_beliefs/docs/belief_history_ridgeline.png
timely_beliefs/docs/comparing_wind_speed_forecasting_models.png
timely_beliefs/docs/confidence.md
timely_beliefs/docs/db.md
timely_beliefs/docs/fixed_viewpoint_ridgeline.png
timely_beliefs/docs/init.md
timely_beliefs/docs/lineage.md
timely_beliefs/docs/resampling.md
timely_beliefs/docs/slicing.md
timely_beliefs/docs/timing.md
timely_beliefs/docs/viz.md
timely_beliefs/examples/__init__.py
timely_beliefs/examples/beliefs_data_frames.py
timely_beliefs/examples/chart.html
timely_beliefs/examples/locale_datetime_sample.csv
timely_beliefs/examples/temperature.csv
timely_beliefs/examples/timezone_naive_sample.csv
timely_beliefs/examples/visualize_example.py
timely_beliefs/sensors/__init__.py
timely_beliefs/sensors/classes.py
timely_beliefs/sensors/utils.py
timely_beliefs/sensors/func_store/__init__.py
timely_beliefs/sensors/func_store/event_values.py
timely_beliefs/sensors/func_store/knowledge_horizons.py
timely_beliefs/sensors/func_store/test_knowledge_horizons.py
timely_beliefs/sensors/func_store/utils.py
timely_beliefs/sources/__init__.py
timely_beliefs/sources/classes.py
timely_beliefs/sources/utils.py
timely_beliefs/tests/README.md
timely_beliefs/tests/__init__.py
timely_beliefs/tests/conftest.py
timely_beliefs/tests/test_accuracy.py
timely_beliefs/tests/test_belief_init.py
timely_beliefs/tests/test_belief_io.py
timely_beliefs/tests/test_belief_persistence.py
timely_beliefs/tests/test_belief_query.py
timely_beliefs/tests/test_belief_utils.py
timely_beliefs/tests/test_db_subclassing.py
timely_beliefs/tests/test_df_resampling.py
timely_beliefs/tests/test_forecast__belief_formation.py
timely_beliefs/tests/test_ignore_36__belief_init.py
timely_beliefs-3.5.0.dist-info/licenses/LICENSE
timely_beliefs-3.5.0.dist-info/METADATA
timely_beliefs-3.5.0.dist-info/WHEEL
timely_beliefs-3.5.0.dist-info/top_level.txt
timely_beliefs-3.5.0.dist-info/RECORD
